Workbook

Sheet Read me
A1: AI productivity ROI calculator
A3: What this is. A working model for the value of giving a team agentic AI tooling, built on the Forrester Total Economic Impact shape: benefits, costs, and a risk adjustment applied to both. It reports two numbers because leadership asks for one and finance asks for the other.
A5: THE TWO NUMBERS, AND WHY BOTH ARE HERE
A6: Benefit dollars is the gross annual value created. It is the number most people mean when they say ROI in conversation.
A7: ROI percent is (benefit minus cost) divided by cost. It is what the word actually means, and it is what a finance reviewer will check.
A8: Quoting one when your audience wanted the other is the most common way this conversation goes wrong. The model shows both, side by side, so you never have to pick in the room.
A10: HOW TO USE IT
A11: Edit only the shaded cells on the Inputs sheet. Everything on Model is a formula and will recalculate. Nothing here connects to a live system, so you can put any numbers in it.
A13: THE ASSUMPTION THAT MATTERS MOST
A14: The realization factor. Time saved is not the same thing as value created. An hour freed up only becomes money if it goes into work that matters, and published studies repeatedly find teams capturing a fraction of their measured time savings. The default here is deliberately conservative. Raising it is the single easiest way to make this model say whatever you want, which is exactly why it is a visible input rather than buried in a coefficient.
A16: THE CAVEAT TO SAY OUT LOUD
A17: Every benchmark on the Benchmarks sheet measures software developers. This model is being applied to a team that mostly does not write software for a living. The hours-saved figure is therefore an anchor and not an estimate, and it should be replaced with a measured number from your own team as soon as one exists. Until then, say so when you present it.
A19: No macros. Everything is formulas, so the file opens anywhere without a security prompt.

Sheet Inputs
A1: Assumption | B1: Value | C1: Unit | D1: Where this comes from
A2: People in scope | B2: 5 | C2: people | D2: How many get a seat. Change this first.
A3: Fully loaded cost per person | B3: 185000 | C3: USD/year | D3: Salary plus benefits, overhead and employer taxes. Ask finance for the real multiplier rather than guessing at 1.3x.
A4: Working hours per year | B4: 1880 | C4: hours | D4: 47 working weeks at 40 hours, which nets off holiday and leave.
A5: Hours saved per person per week | B5: 3.6 | C5: hours | D5: Benchmarks!A4. Developer figure. Replace with a measured number for this team as soon as one exists.
A6: Adoption rate | B6: 0.7 | C6: share | D6: Share of seats in genuine weekly use. A seat nobody opens produces nothing and still costs.
A7: Realization factor | B7: 0.4 | C7: share | D7: Share of freed time that becomes work of comparable value. The most contested input in the model. See Read me.
A8: Seat cost per person | B8: 1000 | C8: USD/month | D8: The platform spending limit per seat. This is a ceiling and not a forecast.
A9: Expected usage per person | B9: 150 | C9: USD/month | D9: What is actually consumed. Keep this separate from the ceiling or the model overstates cost by several times.
A10: Token and API spend outside seats | B10: 0 | C10: USD/month | D10: Automated runs, evaluations and CI. These cannot sit on a human seat. Leaving this at zero is the most common way an AI ROI model flatters itself.
A11: Enablement cost, one off | B11: 12000 | C11: USD | D11: Training, the hours spent learning, and the sessions that teach it. Year one only.
A12: Risk adjustment | B12: 0.2 | C12: share | D12: Forrester TEI applies a haircut to benefits for delivery risk. 20 percent is a common starting point for a first deployment.
A13: Discount rate | B13: 0.1 | C13: share | D13: For the three year net present value. Use whatever finance uses.
A15: Shaded cells are yours to change. Nothing else on this sheet is an input.

Sheet Model
A1: Three year model, risk adjusted
A3: Line | B3: Year 1 | C3: Year 2 | D3: Year 3 | E3: How it is calculated
A4: BENEFITS
A5: Hours freed per year | B5: =Inputs!$B$2*Inputs!$B$5*47*Inputs!$B$6 | C5: =Inputs!$B$2*Inputs!$B$5*47*Inputs!$B$6 | D5: =Inputs!$B$2*Inputs!$B$5*47*Inputs!$B$6 | E5: People x hours per week x 47 weeks x adoption
A6: Gross value of freed time | B6: =Inputs!$B$2*Inputs!$B$5*47*(Inputs!$B$3/Inputs!$B$4)*Inputs!$B$6 | C6: =Inputs!$B$2*Inputs!$B$5*47*(Inputs!$B$3/Inputs!$B$4)*Inputs!$B$6 | D6: =Inputs!$B$2*Inputs!$B$5*47*(Inputs!$B$3/Inputs!$B$4)*Inputs!$B$6 | E6: Hours freed x fully loaded hourly rate
A7: Value actually captured | B7: =Inputs!$B$2*Inputs!$B$5*47*(Inputs!$B$3/Inputs!$B$4)*Inputs!$B$6*Inputs!$B$7 | C7: =Inputs!$B$2*Inputs!$B$5*47*(Inputs!$B$3/Inputs!$B$4)*Inputs!$B$6*Inputs!$B$7 | D7: =Inputs!$B$2*Inputs!$B$5*47*(Inputs!$B$3/Inputs!$B$4)*Inputs!$B$6*Inputs!$B$7 | E7: Gross value x realization factor
A8: Risk adjusted benefit | B8: =Inputs!$B$2*Inputs!$B$5*47*(Inputs!$B$3/Inputs!$B$4)*Inputs!$B$6*Inputs!$B$7*(1-Inputs!$B$12) | C8: =Inputs!$B$2*Inputs!$B$5*47*(Inputs!$B$3/Inputs!$B$4)*Inputs!$B$6*Inputs!$B$7*(1-Inputs!$B$12) | D8: =Inputs!$B$2*Inputs!$B$5*47*(Inputs!$B$3/Inputs!$B$4)*Inputs!$B$6*Inputs!$B$7*(1-Inputs!$B$12) | E8: Captured value less the risk haircut. THIS IS THE BENEFIT NUMBER.
A9: COSTS
A10: Seat usage | B10: =-Inputs!$B$2*Inputs!$B$9*12 | C10: =-Inputs!$B$2*Inputs!$B$9*12 | D10: =-Inputs!$B$2*Inputs!$B$9*12 | E10: Expected usage per person x 12. Not the ceiling.
A11: Token and API spend outside seats | B11: =-Inputs!$B$10*12 | C11: =-Inputs!$B$10*12 | D11: =-Inputs!$B$10*12 | E11: Automation and evaluation runs, which cannot sit on a human seat
A12: Enablement | B12: =-Inputs!$B$11 | C12: 0 | D12: 0 | E12: One off, year one
A13: Total cost | B13: =B10+B11+B12 | C13: =C10+C11+C12 | D13: =D10+D11+D12 | E13: Sum of the three above. Negative, because it is a cost.
A14: RESULT
A15: Net benefit | B15: =B8+B13 | C15: =C8+C13 | D15: =D8+D13 | E15: Risk adjusted benefit less total cost
A16: ROI percent | B16: =IF(B13=0,"",(B8+B13)/-B13) | C16: =IF(C13=0,"",(C8+C13)/-C13) | D16: =IF(D13=0,"",(D8+D13)/-D13) | E16: Net benefit divided by cost. THIS IS THE ROI NUMBER.
A18: Three year net present value | B18: =NPV(Inputs!$B$13,B15,C15,D15) | E18: Net benefit discounted at the rate on Inputs
A19: Payback, months | B19: =IF(B8<=0,"never at these inputs",12*(-B13)/B8) | E19: Year one cost divided by the monthly rate of risk adjusted benefit
A21: Every figure here is driven by the Inputs sheet. If a number looks wrong, the argument is about an assumption, which is the conversation worth having.

Sheet Benchmarks
A1: Figure | B1: Value | C1: What it measures | D1: Source | E1: Captured
A2: Hours saved per week | B2: 3.6 | C2: Across 135,000 plus developers. The most widely cited baseline. | D2: faros.ai analysis | E2: 2026-09-23
A3: Hours saved, daily users | B3: 4.1 | C3: Developers using AI tooling every day rather than occasionally. | D3: faros.ai analysis | E3: 2026-09-23
A4: Healthy ROI range | B4: 2.5x to 3.5x | C4: Average. Top quartile reaches 4x to 6x. Only holds when the cost side includes token spend rather than seat fees alone. | D4: Enterprise AI coding ROI survey round-up | E4: 2026-09-23
A5: Typical productivity gain | B5: 10 to 15 percent | C5: Gains that do NOT reliably convert into business value. | D5: Enterprise AI coding ROI survey round-up | E5: 2026-09-23
A6: Gain when workflows are rebuilt | B6: 25 to 30 percent | C6: Organisations that redesigned how work flows rather than adding a tool to it. | D6: Enterprise AI coding ROI survey round-up | E6: 2026-09-23
A7: Time to measurable ROI | B7: 3 to 6 months | C7: Most enterprise deployments. | D7: Enterprise AI coding ROI survey round-up | E7: 2026-09-23
A8: Framework | B8: Forrester TEI | C8: Benefits, costs, flexibility and risk, with a risk adjustment applied to both sides and results expressed as risk adjusted ROI, NPV and payback. | D8: Forrester Total Economic Impact methodology | E8: 2026-09-23
A10: EVERY FIGURE ON THIS SHEET MEASURES SOFTWARE DEVELOPERS. This team is not one. Treat them as an anchor for a conversation, not as an estimate of what this team will save, and replace them with a measured number as soon as one exists.
